{
  "version": 2,
  "data": {
    "default": {
      "27": {
        "type": "UiArc",
        "id": 27,
        "name": "w1",
        "layer": 3,
        "group": "30",
        "rx": 30,
        "ry": 25,
        "x": 290,
        "y": 551,
        "color": "green",
        "lineWidth": 2,
        "startAngle": 90,
        "endAngle": 217
      },
      "28": {
        "type": "UiArc",
        "id": 28,
        "name": "w2",
        "layer": 3,
        "group": "30",
        "rx": 30,
        "ry": 25,
        "x": 142,
        "y": 551,
        "color": "green",
        "lineWidth": 2,
        "startAngle": 90,
        "endAngle": 217
      },
      "29": {
        "type": "UiArc",
        "id": 29,
        "name": "w3",
        "layer": 3,
        "group": "30",
        "rx": 30,
        "ry": 25,
        "x": 100,
        "y": 546,
        "color": "green",
        "lineWidth": 2,
        "startAngle": 90,
        "endAngle": 270
      },
      "30": {
        "type": "UiArc",
        "id": 30,
        "name": "w4",
        "layer": 3,
        "group": "30",
        "rx": 30,
        "ry": 25,
        "x": 250,
        "y": 546,
        "color": "green",
        "lineWidth": 2,
        "startAngle": 90,
        "endAngle": 270
      },
      "31": {
        "type": "UiRect",
        "id": 31,
        "name": "s1",
        "layer": 3,
        "group": "30",
        "width": 40,
        "height": 20,
        "x": 280,
        "y": 551,
        "color": "green",
        "lineWidth": 2
      },
      "32": {
        "type": "UiRect",
        "id": 32,
        "name": "s2",
        "layer": 3,
        "group": "30",
        "width": 40,
        "height": 20,
        "x": 132,
        "y": 551,
        "color": "green",
        "lineWidth": 2
      },
      "33": {
        "type": "UiRect",
        "id": 33,
        "name": "s3",
        "layer": 3,
        "group": "30",
        "width": 60,
        "height": 25,
        "x": 70,
        "y": 546,
        "color": "green",
        "lineWidth": 2
      },
      "34": {
        "type": "UiRect",
        "id": 34,
        "name": "s4",
        "layer": 3,
        "group": "31",
        "width": 60,
        "height": 25,
        "x": 220,
        "y": 546,
        "color": "green",
        "lineWidth": 2
      },
      "35": {
        "type": "UiRect",
        "id": 35,
        "name": "cap",
        "layer": 3,
        "group": "31",
        "width": 60,
        "height": 20,
        "x": 163,
        "y": 588,
        "color": "green",
        "lineWidth": 2
      },
      "36": {
        "type": "UiRect",
        "id": 36,
        "name": "yaw1",
        "layer": 3,
        "group": "31",
        "width": 275,
        "height": 50,
        "x": 56,
        "y": 573,
        "color": "green",
        "lineWidth": 2
      },
      "37": {
        "type": "UiRect",
        "id": 37,
        "name": "yaw2",
        "layer": 3,
        "group": "31",
        "width": 125,
        "height": 50,
        "x": 116,
        "y": 639,
        "color": "green",
        "lineWidth": 2
      },
      "38": {
        "type": "UiRect",
        "id": 38,
        "name": "pitch",
        "layer": 3,
        "group": "31",
        "width": 80,
        "height": 30,
        "x": 243,
        "y": 648,
        "color": "green",
        "lineWidth": 2
      },
      "39": {
        "type": "UiRect",
        "id": 39,
        "name": "rub_left1",
        "layer": 3,
        "group": "31",
        "width": 12,
        "height": 12,
        "x": 257,
        "y": 663.9999999999999,
        "color": "green",
        "lineWidth": 2
      },
      "40": {
        "type": "UiRect",
        "id": 40,
        "name": "rub_right1",
        "layer": 3,
        "group": "31",
        "width": 12,
        "height": 12,
        "x": 257,
        "y": 650,
        "color": "green",
        "lineWidth": 2
      },
      "41": {
        "type": "UiRect",
        "id": 41,
        "name": "rub_left2",
        "layer": 3,
        "group": "32",
        "width": 12,
        "height": 12,
        "x": 271,
        "y": 663.9999999999999,
        "color": "green",
        "lineWidth": 2
      },
      "42": {
        "type": "UiRect",
        "id": 42,
        "name": "rub_right2",
        "layer": 3,
        "group": "32",
        "width": 12,
        "height": 12,
        "x": 271,
        "y": 650,
        "color": "green",
        "lineWidth": 2
      },
      "43": {
        "type": "UiRect",
        "id": 43,
        "name": "shoot",
        "layer": 3,
        "group": "32",
        "width": 75,
        "height": 12,
        "x": 156,
        "y": 625,
        "color": "green",
        "lineWidth": 2
      },
      "44": {
        "type": "UiRect",
        "id": 44,
        "name": "aim",
        "layer": 3,
        "group": "32",
        "width": 25,
        "height": 12,
        "x": 298,
        "y": 680,
        "color": "green",
        "lineWidth": 2
      }
    }
  },
  "selected": "default"
}